gated_state_spaces_pytorch/__init__.py
gated_state_spaces_pytorch/autoregressive_wrapper.py
gated_state_spaces_pytorch/dsconv.py
gated_state_spaces_pytorch/gss.py
gated_state_spaces_pytorch/mhesa.py
gated_state_spaces_pytorch-0.1.0.dist-info/LICENSE
gated_state_spaces_pytorch-0.1.0.dist-info/METADATA
gated_state_spaces_pytorch-0.1.0.dist-info/WHEEL
gated_state_spaces_pytorch-0.1.0.dist-info/top_level.txt
gated_state_spaces_pytorch-0.1.0.dist-info/RECORD
