Metadata-Version: 2.1
Name: gated-state-spaces-pytorch
Version: 0.1.0
Summary: Gated State Spaces - GSS - Pytorch
Home-page: https://github.com/lucidrains/gated-state-spaces-pytorch
Author: Phil Wang
Author-email: lucidrains@gmail.com
License: MIT
Keywords: artificial intelligence,deep learning,state spaces,long context
Classifier: Development Status :: 4 - Beta
Classifier: Intended Audience :: Developers
Classifier: Topic :: Scientific/Engineering :: Artificial Intelligence
Classifier: License :: OSI Approved :: MIT License
Classifier: Programming Language :: Python :: 3.6
License-File: LICENSE
Requires-Dist: einops (>=0.4)
Requires-Dist: scipy
Requires-Dist: torch (>=1.6)
